allure_megauploader/__init__.py
allure_megauploader/admin.py
allure_megauploader/forms.py
allure_megauploader/models.py
allure_megauploader/swagger.py
allure_megauploader/urls.py
allure_megauploader/utils.py
allure_megauploader/views.py
allure_megauploader/api/__init__.py
allure_megauploader/api/serializers.py
allure_megauploader/api/urls.py
allure_megauploader/api/views.py
allure_megauploader/migrations/0001_initial.py
allure_megauploader/migrations/0002_servicetype_description.py
allure_megauploader/migrations/0003_uploaderconfigv2_custom_attributes.py
allure_megauploader/migrations/0004_alter_uploaderconfigv2_labels.py
allure_megauploader/migrations/0005_usertask_error_usertask_plan_usertask_status.py
allure_megauploader/migrations/0006_uploaderconfigv2_add_allure_source.py
allure_megauploader/migrations/0007_uploaderconfigv2_skip_creating_case.py
allure_megauploader/migrations/__init__.py
allure_megauploader/static/allure_uploader_v2/css/bootstrap.min.css
allure_megauploader/static/allure_uploader_v2/css/selectize.default.min.css
allure_megauploader/static/allure_uploader_v2/css/selectize.min.css
allure_megauploader/static/allure_uploader_v2/js/bootstrap.min.js
allure_megauploader/static/allure_uploader_v2/js/jquery-3.3.1.min.js
allure_megauploader/static/allure_uploader_v2/js/selectize.min.js
allure_megauploader/templates/v2_allure_uploader_task_status.html
allure_megauploader/templates/v2_base.html
allure_megauploader/templates/v2_configs_list.html
allure_megauploader/templates/v2_confirm_delete.html
allure_megauploader/templates/v2_confirm_page.html
allure_megauploader/templates/v2_parameters_dropdown.html
allure_megauploader/templates/v2_plans_dropdown.html
allure_megauploader/templates/v2_service_list.html
allure_megauploader/templates/v2_submit_report.html
allure_megauploader/templates/v2_task_list.html
allure_megauploader/templates/v2_uploader_form.html
allure_megauploader/templates/v2_uploaderconfig_form.html
allure_megauploader-0.0.2.dist-info/METADATA
allure_megauploader-0.0.2.dist-info/WHEEL
allure_megauploader-0.0.2.dist-info/entry_points.txt
allure_megauploader-0.0.2.dist-info/top_level.txt
allure_megauploader-0.0.2.dist-info/RECORD
